start_server.py
codelogic_mcp_server/__init__.py
codelogic_mcp_server/handlers.py
codelogic_mcp_server/server.py
codelogic_mcp_server/utils.py
mseep_codelogic_mcp_server-1.0.6.dist-info/licenses/LICENSE
mseep_codelogic_mcp_server-1.0.6.dist-info/METADATA
mseep_codelogic_mcp_server-1.0.6.dist-info/WHEEL
mseep_codelogic_mcp_server-1.0.6.dist-info/entry_points.txt
mseep_codelogic_mcp_server-1.0.6.dist-info/top_level.txt
mseep_codelogic_mcp_server-1.0.6.dist-info/RECORD
